[
    {
        "ID": "inelevenki6840893944_0_4",
        "abbrkey": {},
        "ancestors": [
            {
                "id": "tung1282",
                "label": "Tungusic"
            },
            {
                "id": "nort3417",
                "label": "Northeastern Tungusic"
            },
            {
                "id": "nort3147",
                "label": "Northern Tungusic"
            }
        ],
        "book_metalanguage": "stan1293",
        "categories": [
            "DAT",
            "DIM",
            "DRV",
            "FUT",
            "IMM",
            "INCH",
            "LOC",
            "N",
            "RFL",
            "SG"
        ],
        "citation": "https://hdl.handle.net/11022/0000-0007-FE38-D",
        "clength": 42,
        "coords": [
            94.689,
            61.972
        ],
        "countries": [
            {
                "ISO3166": "CN",
                "label": "China"
            },
            {
                "ISO3166": "MN",
                "label": "Mongolia"
            },
            {
                "ISO3166": "RU",
                "label": "Russian Federation"
            }
        ],
        "doc_ID": 6840893944,
        "entities": [],
        "html": "<div class=\"imtblocks\">\n\t<div class=\"imtblock\">\n\t\t<div class=\"srcblock\">dʼu-ma-kan-mi</div>\n\t\t<div class=\"glossblock\">house-N.DRV1-DIM1-RFL.SG</div>\n\t</div>\n\t<div class=\"imtblock\">\n\t\t<div class=\"srcblock\">_</div>\n\t\t<div class=\"glossblock\">_</div>\n\t</div>\n\t<div class=\"imtblock\">\n\t\t<div class=\"srcblock\">pʼatnʼisa-du-n</div>\n\t\t<div class=\"glossblock\">friday-DAT/LOC-3SG</div>\n\t</div>\n\t<div class=\"imtblock\">\n\t\t<div class=\"srcblock\">iko-l-dʼa-m</div>\n\t\t<div class=\"glossblock\">sing.dance-INCH-FUT.IMM-1SG</div>\n\t</div>\n</div>\n",
        "imtwordsbare": [
            "house-N.DRV1-DIM1-RFL.SG",
            "_",
            "friday-DAT/LOC-3SG",
            "sing.dance-INCH-FUT.IMM-1SG"
        ],
        "language_glottocode": "even1259",
        "language_iso6393": "evn",
        "language_name": "Evenki",
        "licence": "https://creativecommons.org/licenses/by-nc-sa/4.0/",
        "macroareas": [
            "Eurasia"
        ],
        "parententities": [],
        "provider": "inelevenki",
        "rightsholder": "Däbritz, Chris Lasse; Gusev, Valentin; Stoynova, Natalia. 2024. INEL Evenki Corpus. Version 2.0. Publication date 2024-12-31. Archived at Universität Hamburg. https://hdl.handle.net/11022/0000-0007-FE38-D",
        "srcwordsbare": [
            "dʼu-ma-kan-mi",
            "_",
            "pʼatnʼisa-du-n",
            "iko-l-dʼa-m"
        ],
        "trs": "I'll sing(?) about my little chum (…) on friday.",
        "wlength": 4
    },
    {
        "ID": "inelevenki6840893944_5_8",
        "abbrkey": {},
        "ancestors": [
            {
                "id": "tung1282",
                "label": "Tungusic"
            },
            {
                "id": "nort3417",
                "label": "Northeastern Tungusic"
            },
            {
                "id": "nort3147",
                "label": "Northern Tungusic"
            }
        ],
        "book_metalanguage": "stan1293",
        "categories": [
            "DAT",
            "DIM",
            "DRV",
            "FUT",
            "IMM",
            "IN",
            "INCEP",
            "INCH",
            "LOC",
            "N",
            "PL"
        ],
        "citation": "https://hdl.handle.net/11022/0000-0007-FE38-D",
        "clength": 31,
        "coords": [
            94.689,
            61.972
        ],
        "countries": [
            {
                "ISO3166": "CN",
                "label": "China"
            },
            {
                "ISO3166": "MN",
                "label": "Mongolia"
            },
            {
                "ISO3166": "RU",
                "label": "Russian Federation"
            }
        ],
        "doc_ID": 6840893944,
        "entities": [],
        "html": "<div class=\"imtblocks\">\n\t<div class=\"imtblock\">\n\t\t<div class=\"srcblock\">dʼu-ma-kan-du</div>\n\t\t<div class=\"glossblock\">house-N.DRV1-DIM1-DAT/LOC</div>\n\t</div>\n\t<div class=\"imtblock\">\n\t\t<div class=\"srcblock\">_</div>\n\t\t<div class=\"glossblock\">_</div>\n\t</div>\n\t<div class=\"imtblock\">\n\t\t<div class=\"srcblock\">təɣə-si-l-dʼo-p</div>\n\t\t<div class=\"glossblock\">sit.down-INCEP1-INCH-FUT.IMM-1PL.IN</div>\n\t</div>\n</div>\n",
        "imtwordsbare": [
            "house-N.DRV1-DIM1-DAT/LOC",
            "_",
            "sit.down-INCEP1-INCH-FUT.IMM-1PL.IN"
        ],
        "language_glottocode": "even1259",
        "language_iso6393": "evn",
        "language_name": "Evenki",
        "licence": "https://creativecommons.org/licenses/by-nc-sa/4.0/",
        "macroareas": [
            "Eurasia"
        ],
        "parententities": [],
        "provider": "inelevenki",
        "rightsholder": "Däbritz, Chris Lasse; Gusev, Valentin; Stoynova, Natalia. 2024. INEL Evenki Corpus. Version 2.0. Publication date 2024-12-31. Archived at Universität Hamburg. https://hdl.handle.net/11022/0000-0007-FE38-D",
        "srcwordsbare": [
            "dʼu-ma-kan-du",
            "_",
            "təɣə-si-l-dʼo-p"
        ],
        "trs": "We'll sit (…) in the little chum.",
        "wlength": 3
    },
    {
        "ID": "inelevenki6840893944_9_14",
        "abbrkey": {},
        "ancestors": [
            {
                "id": "tung1282",
                "label": "Tungusic"
            },
            {
                "id": "nort3417",
                "label": "Northeastern Tungusic"
            },
            {
                "id": "nort3147",
                "label": "Northern Tungusic"
            }
        ],
        "book_metalanguage": "stan1293",
        "categories": [
            "DIM",
            "NOM",
            "PJR",
            "PL",
            "PRO",
            "SG"
        ],
        "citation": "https://hdl.handle.net/11022/0000-0007-FE38-D",
        "clength": 33,
        "coords": [
            94.689,
            61.972
        ],
        "countries": [
            {
                "ISO3166": "CN",
                "label": "China"
            },
            {
                "ISO3166": "MN",
                "label": "Mongolia"
            },
            {
                "ISO3166": "RU",
                "label": "Russian Federation"
            }
        ],
        "doc_ID": 6840893944,
        "entities": [],
        "html": "<div class=\"imtblocks\">\n\t<div class=\"imtblock\">\n\t\t<div class=\"srcblock\">umno-kon</div>\n\t\t<div class=\"glossblock\">once-DIM1</div>\n\t</div>\n\t<div class=\"imtblock\">\n\t\t<div class=\"srcblock\">aha-mi-ka-r</div>\n\t\t<div class=\"glossblock\">woman-PJR2-DIM1-PL.[NOM]</div>\n\t</div>\n\t<div class=\"imtblock\">\n\t\t<div class=\"srcblock\">girki-l</div>\n\t\t<div class=\"glossblock\">friend-PL.[NOM]</div>\n\t</div>\n\t<div class=\"imtblock\">\n\t\t<div class=\"srcblock\">bi</div>\n\t\t<div class=\"glossblock\">PRO.1SG.[NOM]</div>\n\t</div>\n\t<div class=\"imtblock\">\n\t\t<div class=\"srcblock\">_</div>\n\t\t<div class=\"glossblock\">_</div>\n\t</div>\n</div>\n",
        "imtwordsbare": [
            "once-DIM1",
            "woman-PJR2-DIM1-PL.[NOM]",
            "friend-PL.[NOM]",
            "PRO.1SG.[NOM]",
            "_"
        ],
        "language_glottocode": "even1259",
        "language_iso6393": "evn",
        "language_name": "Evenki",
        "licence": "https://creativecommons.org/licenses/by-nc-sa/4.0/",
        "macroareas": [
            "Eurasia"
        ],
        "parententities": [],
        "provider": "inelevenki",
        "rightsholder": "Däbritz, Chris Lasse; Gusev, Valentin; Stoynova, Natalia. 2024. INEL Evenki Corpus. Version 2.0. Publication date 2024-12-31. Archived at Universität Hamburg. https://hdl.handle.net/11022/0000-0007-FE38-D",
        "srcwordsbare": [
            "umno-kon",
            "aha-mi-ka-r",
            "girki-l",
            "bi",
            "_"
        ],
        "trs": "Sometimes such little women, friends, I (…).",
        "wlength": 5
    },
    {
        "ID": "inelevenki6840893944_15_17",
        "abbrkey": {},
        "ancestors": [
            {
                "id": "tung1282",
                "label": "Tungusic"
            },
            {
                "id": "nort3417",
                "label": "Northeastern Tungusic"
            },
            {
                "id": "nort3147",
                "label": "Northern Tungusic"
            }
        ],
        "book_metalanguage": "stan1293",
        "categories": [
            "HAB",
            "PL",
            "RHYTM"
        ],
        "citation": "https://hdl.handle.net/11022/0000-0007-FE38-D",
        "clength": 20,
        "coords": [
            94.689,
            61.972
        ],
        "countries": [
            {
                "ISO3166": "CN",
                "label": "China"
            },
            {
                "ISO3166": "MN",
                "label": "Mongolia"
            },
            {
                "ISO3166": "RU",
                "label": "Russian Federation"
            }
        ],
        "doc_ID": 6840893944,
        "entities": [],
        "html": "<div class=\"imtblocks\">\n\t<div class=\"imtblock\">\n\t\t<div class=\"srcblock\">əmə-rə-pki</div>\n\t\t<div class=\"glossblock\">come-RHYTM2-HAB</div>\n\t</div>\n\t<div class=\"imtblock\">\n\t\t<div class=\"srcblock\">əmə-pki-l</div>\n\t\t<div class=\"glossblock\">come-HAB-PL</div>\n\t</div>\n</div>\n",
        "imtwordsbare": [
            "come-RHYTM2-HAB",
            "come-HAB-PL"
        ],
        "language_glottocode": "even1259",
        "language_iso6393": "evn",
        "language_name": "Evenki",
        "licence": "https://creativecommons.org/licenses/by-nc-sa/4.0/",
        "macroareas": [
            "Eurasia"
        ],
        "parententities": [],
        "provider": "inelevenki",
        "rightsholder": "Däbritz, Chris Lasse; Gusev, Valentin; Stoynova, Natalia. 2024. INEL Evenki Corpus. Version 2.0. Publication date 2024-12-31. Archived at Universität Hamburg. https://hdl.handle.net/11022/0000-0007-FE38-D",
        "srcwordsbare": [
            "əmə-rə-pki",
            "əmə-pki-l"
        ],
        "trs": "They use to come.",
        "wlength": 2
    },
    {
        "ID": "inelevenki6840893944_17_23",
        "abbrkey": {},
        "ancestors": [
            {
                "id": "tung1282",
                "label": "Tungusic"
            },
            {
                "id": "nort3417",
                "label": "Northeastern Tungusic"
            },
            {
                "id": "nort3147",
                "label": "Northern Tungusic"
            }
        ],
        "book_metalanguage": "stan1293",
        "categories": [
            "AOR",
            "COND",
            "CVB",
            "DIM",
            "DRV",
            "EVAL",
            "HAB",
            "IPFV",
            "NOM",
            "PL",
            "PRO",
            "SG"
        ],
        "citation": "https://hdl.handle.net/11022/0000-0007-FE38-D",
        "clength": 45,
        "coords": [
            94.689,
            61.972
        ],
        "countries": [
            {
                "ISO3166": "CN",
                "label": "China"
            },
            {
                "ISO3166": "MN",
                "label": "Mongolia"
            },
            {
                "ISO3166": "RU",
                "label": "Russian Federation"
            }
        ],
        "doc_ID": 6840893944,
        "entities": [],
        "html": "<div class=\"imtblocks\">\n\t<div class=\"imtblock\">\n\t\t<div class=\"srcblock\">bi-ma-kan</div>\n\t\t<div class=\"glossblock\">PRO.1SG-EVAL2-DIM1.[NOM]</div>\n\t</div>\n\t<div class=\"imtblock\">\n\t\t<div class=\"srcblock\">_</div>\n\t\t<div class=\"glossblock\">_</div>\n\t</div>\n\t<div class=\"imtblock\">\n\t\t<div class=\"srcblock\">əb-dʼok-tin</div>\n\t\t<div class=\"glossblock\">go.down-CVB.COND-3PL</div>\n\t</div>\n\t<div class=\"imtblock\">\n\t\t<div class=\"srcblock\">bi</div>\n\t\t<div class=\"glossblock\">PRO.1SG.[NOM]</div>\n\t</div>\n\t<div class=\"imtblock\">\n\t\t<div class=\"srcblock\">_</div>\n\t\t<div class=\"glossblock\">_</div>\n\t</div>\n\t<div class=\"imtblock\">\n\t\t<div class=\"srcblock\">kasʼuŋ-dʼa-ŋna-m</div>\n\t\t<div class=\"glossblock\"></div>\n\t</div>\n</div>\n",
        "imtwordsbare": [
            "PRO.1SG-EVAL2-DIM1.[NOM]",
            "_",
            "go.down-CVB.COND-3PL",
            "PRO.1SG.[NOM]",
            "_",
            ""
        ],
        "language_glottocode": "even1259",
        "language_iso6393": "evn",
        "language_name": "Evenki",
        "licence": "https://creativecommons.org/licenses/by-nc-sa/4.0/",
        "macroareas": [
            "Eurasia"
        ],
        "parententities": [],
        "provider": "inelevenki",
        "rightsholder": "Däbritz, Chris Lasse; Gusev, Valentin; Stoynova, Natalia. 2024. INEL Evenki Corpus. Version 2.0. Publication date 2024-12-31. Archived at Universität Hamburg. https://hdl.handle.net/11022/0000-0007-FE38-D",
        "srcwordsbare": [
            "bi-ma-kan",
            "_",
            "əb-dʼok-tin",
            "bi",
            "_",
            "kasʼuŋ-dʼa-ŋna-m"
        ],
        "trs": "And I (…) when they come, I (…) use to make noise.",
        "wlength": 6
    },
    {
        "ID": "inelevenki6840893944_23_26",
        "abbrkey": {},
        "ancestors": [
            {
                "id": "tung1282",
                "label": "Tungusic"
            },
            {
                "id": "nort3417",
                "label": "Northeastern Tungusic"
            },
            {
                "id": "nort3147",
                "label": "Northern Tungusic"
            }
        ],
        "book_metalanguage": "stan1293",
        "categories": [
            "NOM"
        ],
        "citation": "https://hdl.handle.net/11022/0000-0007-FE38-D",
        "clength": 11,
        "coords": [
            94.689,
            61.972
        ],
        "countries": [
            {
                "ISO3166": "CN",
                "label": "China"
            },
            {
                "ISO3166": "MN",
                "label": "Mongolia"
            },
            {
                "ISO3166": "RU",
                "label": "Russian Federation"
            }
        ],
        "doc_ID": 6840893944,
        "entities": [],
        "html": "<div class=\"imtblocks\">\n\t<div class=\"imtblock\">\n\t\t<div class=\"srcblock\">babuska</div>\n\t\t<div class=\"glossblock\">grandmother.[NOM]</div>\n\t</div>\n\t<div class=\"imtblock\">\n\t\t<div class=\"srcblock\">_</div>\n\t\t<div class=\"glossblock\">_</div>\n\t</div>\n\t<div class=\"imtblock\">\n\t\t<div class=\"srcblock\">_</div>\n\t\t<div class=\"glossblock\">_</div>\n\t</div>\n</div>\n",
        "imtwordsbare": [
            "grandmother.[NOM]",
            "_",
            "_"
        ],
        "language_glottocode": "even1259",
        "language_iso6393": "evn",
        "language_name": "Evenki",
        "licence": "https://creativecommons.org/licenses/by-nc-sa/4.0/",
        "macroareas": [
            "Eurasia"
        ],
        "parententities": [],
        "provider": "inelevenki",
        "rightsholder": "Däbritz, Chris Lasse; Gusev, Valentin; Stoynova, Natalia. 2024. INEL Evenki Corpus. Version 2.0. Publication date 2024-12-31. Archived at Universität Hamburg. https://hdl.handle.net/11022/0000-0007-FE38-D",
        "srcwordsbare": [
            "babuska",
            "_",
            "_"
        ],
        "trs": "Grandmother, are you here?",
        "wlength": 3
    },
    {
        "ID": "inelevenki6840893944_27_28",
        "abbrkey": {},
        "ancestors": [
            {
                "id": "tung1282",
                "label": "Tungusic"
            },
            {
                "id": "nort3417",
                "label": "Northeastern Tungusic"
            },
            {
                "id": "nort3147",
                "label": "Northern Tungusic"
            }
        ],
        "book_metalanguage": "stan1293",
        "categories": [],
        "citation": "https://hdl.handle.net/11022/0000-0007-FE38-D",
        "clength": 3,
        "coords": [
            94.689,
            61.972
        ],
        "countries": [
            {
                "ISO3166": "CN",
                "label": "China"
            },
            {
                "ISO3166": "MN",
                "label": "Mongolia"
            },
            {
                "ISO3166": "RU",
                "label": "Russian Federation"
            }
        ],
        "doc_ID": 6840893944,
        "entities": [],
        "html": "<div class=\"imtblocks\">\n\t<div class=\"imtblock\">\n\t\t<div class=\"srcblock\">aha</div>\n\t\t<div class=\"glossblock\">aha</div>\n\t</div>\n</div>\n",
        "imtwordsbare": [
            "aha"
        ],
        "language_glottocode": "even1259",
        "language_iso6393": "evn",
        "language_name": "Evenki",
        "licence": "https://creativecommons.org/licenses/by-nc-sa/4.0/",
        "macroareas": [
            "Eurasia"
        ],
        "parententities": [],
        "provider": "inelevenki",
        "rightsholder": "Däbritz, Chris Lasse; Gusev, Valentin; Stoynova, Natalia. 2024. INEL Evenki Corpus. Version 2.0. Publication date 2024-12-31. Archived at Universität Hamburg. https://hdl.handle.net/11022/0000-0007-FE38-D",
        "srcwordsbare": [
            "aha"
        ],
        "trs": "Aha.",
        "wlength": 1
    },
    {
        "ID": "inelevenki6840893944_28_32",
        "abbrkey": {},
        "ancestors": [
            {
                "id": "tung1282",
                "label": "Tungusic"
            },
            {
                "id": "nort3417",
                "label": "Northeastern Tungusic"
            },
            {
                "id": "nort3147",
                "label": "Northern Tungusic"
            }
        ],
        "book_metalanguage": "stan1293",
        "categories": [
            "NOM",
            "SG"
        ],
        "citation": "https://hdl.handle.net/11022/0000-0007-FE38-D",
        "clength": 18,
        "coords": [
            94.689,
            61.972
        ],
        "countries": [
            {
                "ISO3166": "CN",
                "label": "China"
            },
            {
                "ISO3166": "MN",
                "label": "Mongolia"
            },
            {
                "ISO3166": "RU",
                "label": "Russian Federation"
            }
        ],
        "doc_ID": 6840893944,
        "entities": [],
        "html": "<div class=\"imtblocks\">\n\t<div class=\"imtblock\">\n\t\t<div class=\"srcblock\">eːj</div>\n\t\t<div class=\"glossblock\">hey</div>\n\t</div>\n\t<div class=\"imtblock\">\n\t\t<div class=\"srcblock\">_</div>\n\t\t<div class=\"glossblock\">_</div>\n\t</div>\n\t<div class=\"imtblock\">\n\t\t<div class=\"srcblock\">da</div>\n\t\t<div class=\"glossblock\">but</div>\n\t</div>\n\t<div class=\"imtblock\">\n\t\t<div class=\"srcblock\">babuska-m</div>\n\t\t<div class=\"glossblock\">grandmother.[NOM]-</div>\n\t</div>\n</div>\n",
        "imtwordsbare": [
            "hey",
            "_",
            "but",
            "grandmother.[NOM]-"
        ],
        "language_glottocode": "even1259",
        "language_iso6393": "evn",
        "language_name": "Evenki",
        "licence": "https://creativecommons.org/licenses/by-nc-sa/4.0/",
        "macroareas": [
            "Eurasia"
        ],
        "parententities": [],
        "provider": "inelevenki",
        "rightsholder": "Däbritz, Chris Lasse; Gusev, Valentin; Stoynova, Natalia. 2024. INEL Evenki Corpus. Version 2.0. Publication date 2024-12-31. Archived at Universität Hamburg. https://hdl.handle.net/11022/0000-0007-FE38-D",
        "srcwordsbare": [
            "eːj",
            "_",
            "da",
            "babuska-m"
        ],
        "trs": "Hey, (…) my grandmother.",
        "wlength": 4
    },
    {
        "ID": "inelevenki6840893944_32_37",
        "abbrkey": {},
        "ancestors": [
            {
                "id": "tung1282",
                "label": "Tungusic"
            },
            {
                "id": "nort3417",
                "label": "Northeastern Tungusic"
            },
            {
                "id": "nort3147",
                "label": "Northern Tungusic"
            }
        ],
        "book_metalanguage": "stan1293",
        "categories": [],
        "citation": "https://hdl.handle.net/11022/0000-0007-FE38-D",
        "clength": 9,
        "coords": [
            94.689,
            61.972
        ],
        "countries": [
            {
                "ISO3166": "CN",
                "label": "China"
            },
            {
                "ISO3166": "MN",
                "label": "Mongolia"
            },
            {
                "ISO3166": "RU",
                "label": "Russian Federation"
            }
        ],
        "doc_ID": 6840893944,
        "entities": [],
        "html": "<div class=\"imtblocks\">\n\t<div class=\"imtblock\">\n\t\t<div class=\"srcblock\">_</div>\n\t\t<div class=\"glossblock\">_</div>\n\t</div>\n\t<div class=\"imtblock\">\n\t\t<div class=\"srcblock\">_</div>\n\t\t<div class=\"glossblock\">_</div>\n\t</div>\n\t<div class=\"imtblock\">\n\t\t<div class=\"srcblock\">_</div>\n\t\t<div class=\"glossblock\">_</div>\n\t</div>\n\t<div class=\"imtblock\">\n\t\t<div class=\"srcblock\">_</div>\n\t\t<div class=\"glossblock\">_</div>\n\t</div>\n\t<div class=\"imtblock\">\n\t\t<div class=\"srcblock\">_</div>\n\t\t<div class=\"glossblock\">_</div>\n\t</div>\n</div>\n",
        "imtwordsbare": [
            "_",
            "_",
            "_",
            "_",
            "_"
        ],
        "language_glottocode": "even1259",
        "language_iso6393": "evn",
        "language_name": "Evenki",
        "licence": "https://creativecommons.org/licenses/by-nc-sa/4.0/",
        "macroareas": [
            "Eurasia"
        ],
        "parententities": [],
        "provider": "inelevenki",
        "rightsholder": "Däbritz, Chris Lasse; Gusev, Valentin; Stoynova, Natalia. 2024. INEL Evenki Corpus. Version 2.0. Publication date 2024-12-31. Archived at Universität Hamburg. https://hdl.handle.net/11022/0000-0007-FE38-D",
        "srcwordsbare": [
            "_",
            "_",
            "_",
            "_",
            "_"
        ],
        "trs": "How good, smoke, poor woman(?).",
        "wlength": 5
    },
    {
        "ID": "inelevenki6840893944_38_43",
        "abbrkey": {},
        "ancestors": [
            {
                "id": "tung1282",
                "label": "Tungusic"
            },
            {
                "id": "nort3417",
                "label": "Northeastern Tungusic"
            },
            {
                "id": "nort3147",
                "label": "Northern Tungusic"
            }
        ],
        "book_metalanguage": "stan1293",
        "categories": [
            "AOR",
            "ATTR",
            "DAT",
            "DIM",
            "LOC",
            "NOM",
            "PL",
            "PRO",
            "SG"
        ],
        "citation": "https://hdl.handle.net/11022/0000-0007-FE38-D",
        "clength": 31,
        "coords": [
            94.689,
            61.972
        ],
        "countries": [
            {
                "ISO3166": "CN",
                "label": "China"
            },
            {
                "ISO3166": "MN",
                "label": "Mongolia"
            },
            {
                "ISO3166": "RU",
                "label": "Russian Federation"
            }
        ],
        "doc_ID": 6840893944,
        "entities": [],
        "html": "<div class=\"imtblocks\">\n\t<div class=\"imtblock\">\n\t\t<div class=\"srcblock\">min-ŋi</div>\n\t\t<div class=\"glossblock\">PRO.1SG-ATTR.[NOM]</div>\n\t</div>\n\t<div class=\"imtblock\">\n\t\t<div class=\"srcblock\">girki-l</div>\n\t\t<div class=\"glossblock\">friend-PL.[NOM]</div>\n\t</div>\n\t<div class=\"imtblock\">\n\t\t<div class=\"srcblock\">bi</div>\n\t\t<div class=\"glossblock\">PRO.1SG.[NOM]</div>\n\t</div>\n\t<div class=\"imtblock\">\n\t\t<div class=\"srcblock\">bi-hi</div>\n\t\t<div class=\"glossblock\">be-AOR</div>\n\t</div>\n\t<div class=\"imtblock\">\n\t\t<div class=\"srcblock\">ə-kə-du</div>\n\t\t<div class=\"glossblock\">this-DIM1-DAT/LOC</div>\n\t</div>\n</div>\n",
        "imtwordsbare": [
            "PRO.1SG-ATTR.[NOM]",
            "friend-PL.[NOM]",
            "PRO.1SG.[NOM]",
            "be-AOR",
            "this-DIM1-DAT/LOC"
        ],
        "language_glottocode": "even1259",
        "language_iso6393": "evn",
        "language_name": "Evenki",
        "licence": "https://creativecommons.org/licenses/by-nc-sa/4.0/",
        "macroareas": [
            "Eurasia"
        ],
        "parententities": [],
        "provider": "inelevenki",
        "rightsholder": "Däbritz, Chris Lasse; Gusev, Valentin; Stoynova, Natalia. 2024. INEL Evenki Corpus. Version 2.0. Publication date 2024-12-31. Archived at Universität Hamburg. https://hdl.handle.net/11022/0000-0007-FE38-D",
        "srcwordsbare": [
            "min-ŋi",
            "girki-l",
            "bi",
            "bi-hi",
            "ə-kə-du"
        ],
        "trs": "My friends, I am(?) here.",
        "wlength": 5
    },
    {
        "ID": "inelevenki6840893944_44_48",
        "abbrkey": {},
        "ancestors": [
            {
                "id": "tung1282",
                "label": "Tungusic"
            },
            {
                "id": "nort3417",
                "label": "Northeastern Tungusic"
            },
            {
                "id": "nort3147",
                "label": "Northern Tungusic"
            }
        ],
        "book_metalanguage": "stan1293",
        "categories": [
            "L",
            "NOM",
            "SG"
        ],
        "citation": "https://hdl.handle.net/11022/0000-0007-FE38-D",
        "clength": 23,
        "coords": [
            94.689,
            61.972
        ],
        "countries": [
            {
                "ISO3166": "CN",
                "label": "China"
            },
            {
                "ISO3166": "MN",
                "label": "Mongolia"
            },
            {
                "ISO3166": "RU",
                "label": "Russian Federation"
            }
        ],
        "doc_ID": 6840893944,
        "entities": [
            {
                "label": "Lena",
                "wdid": "Q6522070"
            }
        ],
        "html": "<div class=\"imtblocks\">\n\t<div class=\"imtblock\">\n\t\t<div class=\"srcblock\">girki-w</div>\n\t\t<div class=\"glossblock\">friend.[NOM]-1SG</div>\n\t</div>\n\t<div class=\"imtblock\">\n\t\t<div class=\"srcblock\">Lʼena</div>\n\t\t<div class=\"glossblock\">Lena.[NOM]</div>\n\t</div>\n\t<div class=\"imtblock\">\n\t\t<div class=\"srcblock\">muŋnaːk</div>\n\t\t<div class=\"glossblock\">poor.one</div>\n\t</div>\n\t<div class=\"imtblock\">\n\t\t<div class=\"srcblock\">_</div>\n\t\t<div class=\"glossblock\">_</div>\n\t</div>\n</div>\n",
        "imtwordsbare": [
            "friend.[NOM]-1SG",
            "Lena.[NOM]",
            "poor.one",
            "_"
        ],
        "language_glottocode": "even1259",
        "language_iso6393": "evn",
        "language_name": "Evenki",
        "licence": "https://creativecommons.org/licenses/by-nc-sa/4.0/",
        "macroareas": [
            "Eurasia"
        ],
        "parententities": [],
        "provider": "inelevenki",
        "rightsholder": "Däbritz, Chris Lasse; Gusev, Valentin; Stoynova, Natalia. 2024. INEL Evenki Corpus. Version 2.0. Publication date 2024-12-31. Archived at Universität Hamburg. https://hdl.handle.net/11022/0000-0007-FE38-D",
        "srcwordsbare": [
            "girki-w",
            "Lʼena",
            "muŋnaːk",
            "_"
        ],
        "trs": "My friend Lena, the poor one, died.",
        "wlength": 4
    },
    {
        "abbrkey": {},
        "ancestors": [],
        "book_metalanguage": "stan1293",
        "categories": [
            "DIM",
            "NOM",
            "SG"
        ],
        "doc_ID": 6840893944,
        "entities": [],
        "licence": "https://creativecommons.org/licenses/by-nc-sa/4.0/",
        "macroareas": [],
        "parententities": [],
        "provider": "inelevenki",
        "rightsholder": "Däbritz, Chris Lasse; Gusev, Valentin; Stoynova, Natalia. 2024. INEL Evenki Corpus. Version 2.0. Publication date 2024-12-31. Archived at Universität Hamburg. https://hdl.handle.net/11022/0000-0007-FE38-D"
    },
    {
        "ID": "inelevenki6840893944_52_56",
        "abbrkey": {},
        "ancestors": [
            {
                "id": "tung1282",
                "label": "Tungusic"
            },
            {
                "id": "nort3417",
                "label": "Northeastern Tungusic"
            },
            {
                "id": "nort3147",
                "label": "Northern Tungusic"
            }
        ],
        "book_metalanguage": "stan1293",
        "categories": [
            "ACC",
            "AOR",
            "D",
            "PST",
            "SG"
        ],
        "citation": "https://hdl.handle.net/11022/0000-0007-FE38-D",
        "clength": 29,
        "coords": [
            94.689,
            61.972
        ],
        "countries": [
            {
                "ISO3166": "CN",
                "label": "China"
            },
            {
                "ISO3166": "MN",
                "label": "Mongolia"
            },
            {
                "ISO3166": "RU",
                "label": "Russian Federation"
            }
        ],
        "doc_ID": 6840893944,
        "entities": [
            {
                "label": "Dudinka",
                "wdid": "Q135482"
            }
        ],
        "html": "<div class=\"imtblocks\">\n\t<div class=\"imtblock\">\n\t\t<div class=\"srcblock\">goro-wo</div>\n\t\t<div class=\"glossblock\">long/distant-ACC</div>\n\t</div>\n\t<div class=\"imtblock\">\n\t\t<div class=\"srcblock\">o-sa</div>\n\t\t<div class=\"glossblock\">become-PST.[3SG]</div>\n\t</div>\n\t<div class=\"imtblock\">\n\t\t<div class=\"srcblock\">be-he-m</div>\n\t\t<div class=\"glossblock\">be-AOR-1SG</div>\n\t</div>\n\t<div class=\"imtblock\">\n\t\t<div class=\"srcblock\">Dudʼinku</div>\n\t\t<div class=\"glossblock\">Dudinka.ACC</div>\n\t</div>\n</div>\n",
        "imtwordsbare": [
            "long/distant-ACC",
            "become-PST.[3SG]",
            "be-AOR-1SG",
            "Dudinka.ACC"
        ],
        "language_glottocode": "even1259",
        "language_iso6393": "evn",
        "language_name": "Evenki",
        "licence": "https://creativecommons.org/licenses/by-nc-sa/4.0/",
        "macroareas": [
            "Eurasia"
        ],
        "parententities": [],
        "provider": "inelevenki",
        "rightsholder": "Däbritz, Chris Lasse; Gusev, Valentin; Stoynova, Natalia. 2024. INEL Evenki Corpus. Version 2.0. Publication date 2024-12-31. Archived at Universität Hamburg. https://hdl.handle.net/11022/0000-0007-FE38-D",
        "srcwordsbare": [
            "goro-wo",
            "o-sa",
            "be-he-m",
            "Dudʼinku"
        ],
        "trs": "I was for a long time [in] Dudinka.",
        "wlength": 4
    },
    {
        "ID": "inelevenki6840893944_57_64",
        "abbrkey": {},
        "ancestors": [
            {
                "id": "tung1282",
                "label": "Tungusic"
            },
            {
                "id": "nort3417",
                "label": "Northeastern Tungusic"
            },
            {
                "id": "nort3147",
                "label": "Northern Tungusic"
            }
        ],
        "book_metalanguage": "stan1293",
        "categories": [
            "ACC",
            "AOR",
            "D",
            "EMPH",
            "EVAL",
            "NOM",
            "PRO",
            "PST",
            "SG"
        ],
        "citation": "https://hdl.handle.net/11022/0000-0007-FE38-D",
        "clength": 62,
        "coords": [
            94.689,
            61.972
        ],
        "countries": [
            {
                "ISO3166": "CN",
                "label": "China"
            },
            {
                "ISO3166": "MN",
                "label": "Mongolia"
            },
            {
                "ISO3166": "RU",
                "label": "Russian Federation"
            }
        ],
        "doc_ID": 6840893944,
        "entities": [
            {
                "label": "Dudinka",
                "wdid": "Q135482"
            }
        ],
        "html": "<div class=\"imtblocks\">\n\t<div class=\"imtblock\">\n\t\t<div class=\"srcblock\">Dudʼinka</div>\n\t\t<div class=\"glossblock\">Dudinka.[NOM]</div>\n\t</div>\n\t<div class=\"imtblock\">\n\t\t<div class=\"srcblock\">goro-wo</div>\n\t\t<div class=\"glossblock\">long/distant-ACC</div>\n\t</div>\n\t<div class=\"imtblock\">\n\t\t<div class=\"srcblock\">o-sʼa-m</div>\n\t\t<div class=\"glossblock\">become-PST-1SG</div>\n\t</div>\n\t<div class=\"imtblock\">\n\t\t<div class=\"srcblock\">kəhə-do-tə</div>\n\t\t<div class=\"glossblock\">torment-EMPH3-EMPH12</div>\n\t</div>\n\t<div class=\"imtblock\">\n\t\t<div class=\"srcblock\">ara-ma</div>\n\t\t<div class=\"glossblock\">barely-EVAL2</div>\n\t</div>\n\t<div class=\"imtblock\">\n\t\t<div class=\"srcblock\">amin-a-m</div>\n\t\t<div class=\"glossblock\">meet-AOR-1SG</div>\n\t</div>\n\t<div class=\"imtblock\">\n\t\t<div class=\"srcblock\">nuŋan-ma-n</div>\n\t\t<div class=\"glossblock\">PRO.3-ACC-3SG</div>\n\t</div>\n</div>\n",
        "imtwordsbare": [
            "Dudinka.[NOM]",
            "long/distant-ACC",
            "become-PST-1SG",
            "torment-EMPH3-EMPH12",
            "barely-EVAL2",
            "meet-AOR-1SG",
            "PRO.3-ACC-3SG"
        ],
        "language_glottocode": "even1259",
        "language_iso6393": "evn",
        "language_name": "Evenki",
        "licence": "https://creativecommons.org/licenses/by-nc-sa/4.0/",
        "macroareas": [
            "Eurasia"
        ],
        "parententities": [],
        "provider": "inelevenki",
        "rightsholder": "Däbritz, Chris Lasse; Gusev, Valentin; Stoynova, Natalia. 2024. INEL Evenki Corpus. Version 2.0. Publication date 2024-12-31. Archived at Universität Hamburg. https://hdl.handle.net/11022/0000-0007-FE38-D",
        "srcwordsbare": [
            "Dudʼinka",
            "goro-wo",
            "o-sʼa-m",
            "kəhə-do-tə",
            "ara-ma",
            "amin-a-m",
            "nuŋan-ma-n"
        ],
        "trs": "In Dudinka I was for a long time, oj, I hardly met her.",
        "wlength": 7
    },
    {
        "ID": "inelevenki6840893944_65_67",
        "abbrkey": {},
        "ancestors": [
            {
                "id": "tung1282",
                "label": "Tungusic"
            },
            {
                "id": "nort3417",
                "label": "Northeastern Tungusic"
            },
            {
                "id": "nort3147",
                "label": "Northern Tungusic"
            }
        ],
        "book_metalanguage": "stan1293",
        "categories": [
            "AOR",
            "DAT",
            "LOC",
            "SG"
        ],
        "citation": "https://hdl.handle.net/11022/0000-0007-FE38-D",
        "clength": 20,
        "coords": [
            94.689,
            61.972
        ],
        "countries": [
            {
                "ISO3166": "CN",
                "label": "China"
            },
            {
                "ISO3166": "MN",
                "label": "Mongolia"
            },
            {
                "ISO3166": "RU",
                "label": "Russian Federation"
            }
        ],
        "doc_ID": 6840893944,
        "entities": [],
        "html": "<div class=\"imtblocks\">\n\t<div class=\"imtblock\">\n\t\t<div class=\"srcblock\">bəlʼnʼisa-du</div>\n\t\t<div class=\"glossblock\">hospital-DAT/LOC</div>\n\t</div>\n\t<div class=\"imtblock\">\n\t\t<div class=\"srcblock\">bi-he-m</div>\n\t\t<div class=\"glossblock\">be-AOR-1SG</div>\n\t</div>\n</div>\n",
        "imtwordsbare": [
            "hospital-DAT/LOC",
            "be-AOR-1SG"
        ],
        "language_glottocode": "even1259",
        "language_iso6393": "evn",
        "language_name": "Evenki",
        "licence": "https://creativecommons.org/licenses/by-nc-sa/4.0/",
        "macroareas": [
            "Eurasia"
        ],
        "parententities": [],
        "provider": "inelevenki",
        "rightsholder": "Däbritz, Chris Lasse; Gusev, Valentin; Stoynova, Natalia. 2024. INEL Evenki Corpus. Version 2.0. Publication date 2024-12-31. Archived at Universität Hamburg. https://hdl.handle.net/11022/0000-0007-FE38-D",
        "srcwordsbare": [
            "bəlʼnʼisa-du",
            "bi-he-m"
        ],
        "trs": "I was in hospital.",
        "wlength": 2
    },
    {
        "ID": "inelevenki6840893944_68_73",
        "abbrkey": {},
        "ancestors": [
            {
                "id": "tung1282",
                "label": "Tungusic"
            },
            {
                "id": "nort3417",
                "label": "Northeastern Tungusic"
            },
            {
                "id": "nort3147",
                "label": "Northern Tungusic"
            }
        ],
        "book_metalanguage": "stan1293",
        "categories": [
            "AOR",
            "CNG",
            "DAT",
            "EP",
            "ING",
            "LOC",
            "NEG",
            "PST",
            "REC",
            "RFL",
            "SG",
            "VBLZ"
        ],
        "citation": "https://hdl.handle.net/11022/0000-0007-FE38-D",
        "clength": 51,
        "coords": [
            94.689,
            61.972
        ],
        "countries": [
            {
                "ISO3166": "CN",
                "label": "China"
            },
            {
                "ISO3166": "MN",
                "label": "Mongolia"
            },
            {
                "ISO3166": "RU",
                "label": "Russian Federation"
            }
        ],
        "doc_ID": 6840893944,
        "entities": [],
        "html": "<div class=\"imtblocks\">\n\t<div class=\"imtblock\">\n\t\t<div class=\"srcblock\">bəlʼnʼisa-du</div>\n\t\t<div class=\"glossblock\">hospital-DAT/LOC</div>\n\t</div>\n\t<div class=\"imtblock\">\n\t\t<div class=\"srcblock\">bi-he</div>\n\t\t<div class=\"glossblock\">be-AOR</div>\n\t</div>\n\t<div class=\"imtblock\">\n\t\t<div class=\"srcblock\">ə-sə-w</div>\n\t\t<div class=\"glossblock\">NEG-PST-1SG</div>\n\t</div>\n\t<div class=\"imtblock\">\n\t\t<div class=\"srcblock\">sat-ti-mat-i-ra</div>\n\t\t<div class=\"glossblock\">tea-VBLZ.ING-REC-EP-CNG</div>\n\t</div>\n\t<div class=\"imtblock\">\n\t\t<div class=\"srcblock\">dʼu-du-ji</div>\n\t\t<div class=\"glossblock\">house-DAT/LOC-RFL.SG</div>\n\t</div>\n</div>\n",
        "imtwordsbare": [
            "hospital-DAT/LOC",
            "be-AOR",
            "NEG-PST-1SG",
            "tea-VBLZ.ING-REC-EP-CNG",
            "house-DAT/LOC-RFL.SG"
        ],
        "language_glottocode": "even1259",
        "language_iso6393": "evn",
        "language_name": "Evenki",
        "licence": "https://creativecommons.org/licenses/by-nc-sa/4.0/",
        "macroareas": [
            "Eurasia"
        ],
        "parententities": [],
        "provider": "inelevenki",
        "rightsholder": "Däbritz, Chris Lasse; Gusev, Valentin; Stoynova, Natalia. 2024. INEL Evenki Corpus. Version 2.0. Publication date 2024-12-31. Archived at Universität Hamburg. https://hdl.handle.net/11022/0000-0007-FE38-D",
        "srcwordsbare": [
            "bəlʼnʼisa-du",
            "bi-he",
            "ə-sə-w",
            "sat-ti-mat-i-ra",
            "dʼu-du-ji"
        ],
        "trs": "[I] was in hospital, I even didn't drink tea at home.",
        "wlength": 5
    },
    {
        "ID": "inelevenki6840893944_74_76",
        "abbrkey": {},
        "ancestors": [
            {
                "id": "tung1282",
                "label": "Tungusic"
            },
            {
                "id": "nort3417",
                "label": "Northeastern Tungusic"
            },
            {
                "id": "nort3147",
                "label": "Northern Tungusic"
            }
        ],
        "book_metalanguage": "stan1293",
        "categories": [
            "AOR",
            "CVB",
            "SG",
            "SIM"
        ],
        "citation": "https://hdl.handle.net/11022/0000-0007-FE38-D",
        "clength": 15,
        "coords": [
            94.689,
            61.972
        ],
        "countries": [
            {
                "ISO3166": "CN",
                "label": "China"
            },
            {
                "ISO3166": "MN",
                "label": "Mongolia"
            },
            {
                "ISO3166": "RU",
                "label": "Russian Federation"
            }
        ],
        "doc_ID": 6840893944,
        "entities": [],
        "html": "<div class=\"imtblocks\">\n\t<div class=\"imtblock\">\n\t\t<div class=\"srcblock\">huru-m</div>\n\t\t<div class=\"glossblock\">leave.[AOR]-1SG</div>\n\t</div>\n\t<div class=\"imtblock\">\n\t\t<div class=\"srcblock\">tuksa-na</div>\n\t\t<div class=\"glossblock\">run-CVB.SIM1</div>\n\t</div>\n</div>\n",
        "imtwordsbare": [
            "leave.[AOR]-1SG",
            "run-CVB.SIM1"
        ],
        "language_glottocode": "even1259",
        "language_iso6393": "evn",
        "language_name": "Evenki",
        "licence": "https://creativecommons.org/licenses/by-nc-sa/4.0/",
        "macroareas": [
            "Eurasia"
        ],
        "parententities": [],
        "provider": "inelevenki",
        "rightsholder": "Däbritz, Chris Lasse; Gusev, Valentin; Stoynova, Natalia. 2024. INEL Evenki Corpus. Version 2.0. Publication date 2024-12-31. Archived at Universität Hamburg. https://hdl.handle.net/11022/0000-0007-FE38-D",
        "srcwordsbare": [
            "huru-m",
            "tuksa-na"
        ],
        "trs": "I was running around.",
        "wlength": 2
    },
    {
        "ID": "inelevenki6840893944_77_78",
        "abbrkey": {},
        "ancestors": [
            {
                "id": "tung1282",
                "label": "Tungusic"
            },
            {
                "id": "nort3417",
                "label": "Northeastern Tungusic"
            },
            {
                "id": "nort3147",
                "label": "Northern Tungusic"
            }
        ],
        "book_metalanguage": "stan1293",
        "categories": [],
        "citation": "https://hdl.handle.net/11022/0000-0007-FE38-D",
        "clength": 1,
        "coords": [
            94.689,
            61.972
        ],
        "countries": [
            {
                "ISO3166": "CN",
                "label": "China"
            },
            {
                "ISO3166": "MN",
                "label": "Mongolia"
            },
            {
                "ISO3166": "RU",
                "label": "Russian Federation"
            }
        ],
        "doc_ID": 6840893944,
        "entities": [],
        "html": "<div class=\"imtblocks\">\n\t<div class=\"imtblock\">\n\t\t<div class=\"srcblock\">_</div>\n\t\t<div class=\"glossblock\">_</div>\n\t</div>\n</div>\n",
        "imtwordsbare": [
            "_"
        ],
        "language_glottocode": "even1259",
        "language_iso6393": "evn",
        "language_name": "Evenki",
        "licence": "https://creativecommons.org/licenses/by-nc-sa/4.0/",
        "macroareas": [
            "Eurasia"
        ],
        "parententities": [],
        "provider": "inelevenki",
        "rightsholder": "Däbritz, Chris Lasse; Gusev, Valentin; Stoynova, Natalia. 2024. INEL Evenki Corpus. Version 2.0. Publication date 2024-12-31. Archived at Universität Hamburg. https://hdl.handle.net/11022/0000-0007-FE38-D",
        "srcwordsbare": [
            "_"
        ],
        "trs": "",
        "wlength": 1
    },
    {
        "ID": "inelevenki6840893944_79_80",
        "abbrkey": {},
        "ancestors": [
            {
                "id": "tung1282",
                "label": "Tungusic"
            },
            {
                "id": "nort3417",
                "label": "Northeastern Tungusic"
            },
            {
                "id": "nort3147",
                "label": "Northern Tungusic"
            }
        ],
        "book_metalanguage": "stan1293",
        "categories": [
            "IMP",
            "Q",
            "SG"
        ],
        "citation": "https://hdl.handle.net/11022/0000-0007-FE38-D",
        "clength": 10,
        "coords": [
            94.689,
            61.972
        ],
        "countries": [
            {
                "ISO3166": "CN",
                "label": "China"
            },
            {
                "ISO3166": "MN",
                "label": "Mongolia"
            },
            {
                "ISO3166": "RU",
                "label": "Russian Federation"
            }
        ],
        "doc_ID": 6840893944,
        "entities": [],
        "html": "<div class=\"imtblocks\">\n\t<div class=\"imtblock\">\n\t\t<div class=\"srcblock\">iko-ktə-wu</div>\n\t\t<div class=\"glossblock\">sing.dance-IMP.1SG-Q</div>\n\t</div>\n</div>\n",
        "imtwordsbare": [
            "sing.dance-IMP.1SG-Q"
        ],
        "language_glottocode": "even1259",
        "language_iso6393": "evn",
        "language_name": "Evenki",
        "licence": "https://creativecommons.org/licenses/by-nc-sa/4.0/",
        "macroareas": [
            "Eurasia"
        ],
        "parententities": [],
        "provider": "inelevenki",
        "rightsholder": "Däbritz, Chris Lasse; Gusev, Valentin; Stoynova, Natalia. 2024. INEL Evenki Corpus. Version 2.0. Publication date 2024-12-31. Archived at Universität Hamburg. https://hdl.handle.net/11022/0000-0007-FE38-D",
        "srcwordsbare": [
            "iko-ktə-wu"
        ],
        "trs": "I shall sing, though.",
        "wlength": 1
    },
    {
        "ID": "inelevenki6840893944_81_83",
        "abbrkey": {},
        "ancestors": [
            {
                "id": "tung1282",
                "label": "Tungusic"
            },
            {
                "id": "nort3417",
                "label": "Northeastern Tungusic"
            },
            {
                "id": "nort3147",
                "label": "Northern Tungusic"
            }
        ],
        "book_metalanguage": "stan1293",
        "categories": [
            "FUT",
            "IMM",
            "INCH",
            "SG"
        ],
        "citation": "https://hdl.handle.net/11022/0000-0007-FE38-D",
        "clength": 21,
        "coords": [
            94.689,
            61.972
        ],
        "countries": [
            {
                "ISO3166": "CN",
                "label": "China"
            },
            {
                "ISO3166": "MN",
                "label": "Mongolia"
            },
            {
                "ISO3166": "RU",
                "label": "Russian Federation"
            }
        ],
        "doc_ID": 6840893944,
        "entities": [],
        "html": "<div class=\"imtblocks\">\n\t<div class=\"imtblock\">\n\t\t<div class=\"srcblock\">iko-l-dʼe-m</div>\n\t\t<div class=\"glossblock\">sing.dance-INCH-FUT.IMM-1SG</div>\n\t</div>\n\t<div class=\"imtblock\">\n\t\t<div class=\"srcblock\">iko-dʼe-m</div>\n\t\t<div class=\"glossblock\">sing.dance-FUT.IMM-1SG</div>\n\t</div>\n</div>\n",
        "imtwordsbare": [
            "sing.dance-INCH-FUT.IMM-1SG",
            "sing.dance-FUT.IMM-1SG"
        ],
        "language_glottocode": "even1259",
        "language_iso6393": "evn",
        "language_name": "Evenki",
        "licence": "https://creativecommons.org/licenses/by-nc-sa/4.0/",
        "macroareas": [
            "Eurasia"
        ],
        "parententities": [],
        "provider": "inelevenki",
        "rightsholder": "Däbritz, Chris Lasse; Gusev, Valentin; Stoynova, Natalia. 2024. INEL Evenki Corpus. Version 2.0. Publication date 2024-12-31. Archived at Universität Hamburg. https://hdl.handle.net/11022/0000-0007-FE38-D",
        "srcwordsbare": [
            "iko-l-dʼe-m",
            "iko-dʼe-m"
        ],
        "trs": "I'll start singing, I'll sing.",
        "wlength": 2
    },
    {
        "ID": "inelevenki6840893944_83_86",
        "abbrkey": {},
        "ancestors": [
            {
                "id": "tung1282",
                "label": "Tungusic"
            },
            {
                "id": "nort3417",
                "label": "Northeastern Tungusic"
            },
            {
                "id": "nort3147",
                "label": "Northern Tungusic"
            }
        ],
        "book_metalanguage": "stan1293",
        "categories": [
            "DAT",
            "FUT",
            "IMM",
            "INCH",
            "LOC",
            "SG"
        ],
        "citation": "https://hdl.handle.net/11022/0000-0007-FE38-D",
        "clength": 28,
        "coords": [
            94.689,
            61.972
        ],
        "countries": [
            {
                "ISO3166": "CN",
                "label": "China"
            },
            {
                "ISO3166": "MN",
                "label": "Mongolia"
            },
            {
                "ISO3166": "RU",
                "label": "Russian Federation"
            }
        ],
        "doc_ID": 6840893944,
        "entities": [],
        "html": "<div class=\"imtblocks\">\n\t<div class=\"imtblock\">\n\t\t<div class=\"srcblock\">dʼu-du</div>\n\t\t<div class=\"glossblock\">house-DAT/LOC</div>\n\t</div>\n\t<div class=\"imtblock\">\n\t\t<div class=\"srcblock\">iko-l-dʼə-m</div>\n\t\t<div class=\"glossblock\">sing.dance-INCH-FUT.IMM-1SG</div>\n\t</div>\n\t<div class=\"imtblock\">\n\t\t<div class=\"srcblock\">iko-dʼə-m</div>\n\t\t<div class=\"glossblock\">sing.dance-FUT.IMM-1SG</div>\n\t</div>\n</div>\n",
        "imtwordsbare": [
            "house-DAT/LOC",
            "sing.dance-INCH-FUT.IMM-1SG",
            "sing.dance-FUT.IMM-1SG"
        ],
        "language_glottocode": "even1259",
        "language_iso6393": "evn",
        "language_name": "Evenki",
        "licence": "https://creativecommons.org/licenses/by-nc-sa/4.0/",
        "macroareas": [
            "Eurasia"
        ],
        "parententities": [],
        "provider": "inelevenki",
        "rightsholder": "Däbritz, Chris Lasse; Gusev, Valentin; Stoynova, Natalia. 2024. INEL Evenki Corpus. Version 2.0. Publication date 2024-12-31. Archived at Universität Hamburg. https://hdl.handle.net/11022/0000-0007-FE38-D",
        "srcwordsbare": [
            "dʼu-du",
            "iko-l-dʼə-m",
            "iko-dʼə-m"
        ],
        "trs": "I'll start singing at home, I'll sing (?).",
        "wlength": 3
    },
    {
        "ID": "inelevenki6840893944_87_88",
        "abbrkey": {},
        "ancestors": [
            {
                "id": "tung1282",
                "label": "Tungusic"
            },
            {
                "id": "nort3417",
                "label": "Northeastern Tungusic"
            },
            {
                "id": "nort3147",
                "label": "Northern Tungusic"
            }
        ],
        "book_metalanguage": "stan1293",
        "categories": [],
        "citation": "https://hdl.handle.net/11022/0000-0007-FE38-D",
        "clength": 1,
        "coords": [
            94.689,
            61.972
        ],
        "countries": [
            {
                "ISO3166": "CN",
                "label": "China"
            },
            {
                "ISO3166": "MN",
                "label": "Mongolia"
            },
            {
                "ISO3166": "RU",
                "label": "Russian Federation"
            }
        ],
        "doc_ID": 6840893944,
        "entities": [],
        "html": "<div class=\"imtblocks\">\n\t<div class=\"imtblock\">\n\t\t<div class=\"srcblock\">_</div>\n\t\t<div class=\"glossblock\">_</div>\n\t</div>\n</div>\n",
        "imtwordsbare": [
            "_"
        ],
        "language_glottocode": "even1259",
        "language_iso6393": "evn",
        "language_name": "Evenki",
        "licence": "https://creativecommons.org/licenses/by-nc-sa/4.0/",
        "macroareas": [
            "Eurasia"
        ],
        "parententities": [],
        "provider": "inelevenki",
        "rightsholder": "Däbritz, Chris Lasse; Gusev, Valentin; Stoynova, Natalia. 2024. INEL Evenki Corpus. Version 2.0. Publication date 2024-12-31. Archived at Universität Hamburg. https://hdl.handle.net/11022/0000-0007-FE38-D",
        "srcwordsbare": [
            "_"
        ],
        "trs": "",
        "wlength": 1
    },
    {
        "ID": "inelevenki6840893944_89_93",
        "abbrkey": {},
        "ancestors": [
            {
                "id": "tung1282",
                "label": "Tungusic"
            },
            {
                "id": "nort3417",
                "label": "Northeastern Tungusic"
            },
            {
                "id": "nort3147",
                "label": "Northern Tungusic"
            }
        ],
        "book_metalanguage": "stan1293",
        "categories": [
            "AFCT",
            "NOM"
        ],
        "citation": "https://hdl.handle.net/11022/0000-0007-FE38-D",
        "clength": 21,
        "coords": [
            94.689,
            61.972
        ],
        "countries": [
            {
                "ISO3166": "CN",
                "label": "China"
            },
            {
                "ISO3166": "MN",
                "label": "Mongolia"
            },
            {
                "ISO3166": "RU",
                "label": "Russian Federation"
            }
        ],
        "doc_ID": 6840893944,
        "entities": [],
        "html": "<div class=\"imtblocks\">\n\t<div class=\"imtblock\">\n\t\t<div class=\"srcblock\">omolgi</div>\n\t\t<div class=\"glossblock\">boy.[NOM]</div>\n\t</div>\n\t<div class=\"imtblock\">\n\t\t<div class=\"srcblock\">_</div>\n\t\t<div class=\"glossblock\">_</div>\n\t</div>\n\t<div class=\"imtblock\">\n\t\t<div class=\"srcblock\">koto-kokun</div>\n\t\t<div class=\"glossblock\">many-AFCT.[NOM]</div>\n\t</div>\n\t<div class=\"imtblock\">\n\t\t<div class=\"srcblock\">_</div>\n\t\t<div class=\"glossblock\">_</div>\n\t</div>\n</div>\n",
        "imtwordsbare": [
            "boy.[NOM]",
            "_",
            "many-AFCT.[NOM]",
            "_"
        ],
        "language_glottocode": "even1259",
        "language_iso6393": "evn",
        "language_name": "Evenki",
        "licence": "https://creativecommons.org/licenses/by-nc-sa/4.0/",
        "macroareas": [
            "Eurasia"
        ],
        "parententities": [],
        "provider": "inelevenki",
        "rightsholder": "Däbritz, Chris Lasse; Gusev, Valentin; Stoynova, Natalia. 2024. INEL Evenki Corpus. Version 2.0. Publication date 2024-12-31. Archived at Universität Hamburg. https://hdl.handle.net/11022/0000-0007-FE38-D",
        "srcwordsbare": [
            "omolgi",
            "_",
            "koto-kokun",
            "_"
        ],
        "trs": "The boy (…), many (…).",
        "wlength": 4
    },
    {
        "ID": "inelevenki6840893944_94_98",
        "abbrkey": {},
        "ancestors": [
            {
                "id": "tung1282",
                "label": "Tungusic"
            },
            {
                "id": "nort3417",
                "label": "Northeastern Tungusic"
            },
            {
                "id": "nort3147",
                "label": "Northern Tungusic"
            }
        ],
        "book_metalanguage": "stan1293",
        "categories": [
            "NOM"
        ],
        "citation": "https://hdl.handle.net/11022/0000-0007-FE38-D",
        "clength": 15,
        "coords": [
            94.689,
            61.972
        ],
        "countries": [
            {
                "ISO3166": "CN",
                "label": "China"
            },
            {
                "ISO3166": "MN",
                "label": "Mongolia"
            },
            {
                "ISO3166": "RU",
                "label": "Russian Federation"
            }
        ],
        "doc_ID": 6840893944,
        "entities": [],
        "html": "<div class=\"imtblocks\">\n\t<div class=\"imtblock\">\n\t\t<div class=\"srcblock\">_</div>\n\t\t<div class=\"glossblock\">_</div>\n\t</div>\n\t<div class=\"imtblock\">\n\t\t<div class=\"srcblock\">ilan</div>\n\t\t<div class=\"glossblock\">three.[NOM]</div>\n\t</div>\n\t<div class=\"imtblock\">\n\t\t<div class=\"srcblock\">omolgi</div>\n\t\t<div class=\"glossblock\">boy.[NOM]</div>\n\t</div>\n\t<div class=\"imtblock\">\n\t\t<div class=\"srcblock\">_</div>\n\t\t<div class=\"glossblock\">_</div>\n\t</div>\n</div>\n",
        "imtwordsbare": [
            "_",
            "three.[NOM]",
            "boy.[NOM]",
            "_"
        ],
        "language_glottocode": "even1259",
        "language_iso6393": "evn",
        "language_name": "Evenki",
        "licence": "https://creativecommons.org/licenses/by-nc-sa/4.0/",
        "macroareas": [
            "Eurasia"
        ],
        "parententities": [],
        "provider": "inelevenki",
        "rightsholder": "Däbritz, Chris Lasse; Gusev, Valentin; Stoynova, Natalia. 2024. INEL Evenki Corpus. Version 2.0. Publication date 2024-12-31. Archived at Universität Hamburg. https://hdl.handle.net/11022/0000-0007-FE38-D",
        "srcwordsbare": [
            "_",
            "ilan",
            "omolgi",
            "_"
        ],
        "trs": "Three boys died.",
        "wlength": 4
    },
    {
        "ID": "inelevenki6840893944_99_103",
        "abbrkey": {},
        "ancestors": [
            {
                "id": "tung1282",
                "label": "Tungusic"
            },
            {
                "id": "nort3417",
                "label": "Northeastern Tungusic"
            },
            {
                "id": "nort3147",
                "label": "Northern Tungusic"
            }
        ],
        "book_metalanguage": "stan1293",
        "categories": [
            "K",
            "M",
            "S",
            "V"
        ],
        "citation": "https://hdl.handle.net/11022/0000-0007-FE38-D",
        "clength": 25,
        "coords": [
            94.689,
            61.972
        ],
        "countries": [
            {
                "ISO3166": "CN",
                "label": "China"
            },
            {
                "ISO3166": "MN",
                "label": "Mongolia"
            },
            {
                "ISO3166": "RU",
                "label": "Russian Federation"
            }
        ],
        "doc_ID": 6840893944,
        "entities": [],
        "html": "<div class=\"imtblocks\">\n\t<div class=\"imtblock\">\n\t\t<div class=\"srcblock\">Stʼepan</div>\n\t\t<div class=\"glossblock\">Stepan</div>\n\t</div>\n\t<div class=\"imtblock\">\n\t\t<div class=\"srcblock\">Kolʼa</div>\n\t\t<div class=\"glossblock\">Kolya</div>\n\t</div>\n\t<div class=\"imtblock\">\n\t\t<div class=\"srcblock\">Bitʼə</div>\n\t\t<div class=\"glossblock\">Vitya</div>\n\t</div>\n\t<div class=\"imtblock\">\n\t\t<div class=\"srcblock\">Misʼa</div>\n\t\t<div class=\"glossblock\">Misya</div>\n\t</div>\n</div>\n",
        "imtwordsbare": [
            "Stepan",
            "Kolya",
            "Vitya",
            "Misya"
        ],
        "language_glottocode": "even1259",
        "language_iso6393": "evn",
        "language_name": "Evenki",
        "licence": "https://creativecommons.org/licenses/by-nc-sa/4.0/",
        "macroareas": [
            "Eurasia"
        ],
        "parententities": [],
        "provider": "inelevenki",
        "rightsholder": "Däbritz, Chris Lasse; Gusev, Valentin; Stoynova, Natalia. 2024. INEL Evenki Corpus. Version 2.0. Publication date 2024-12-31. Archived at Universität Hamburg. https://hdl.handle.net/11022/0000-0007-FE38-D",
        "srcwordsbare": [
            "Stʼepan",
            "Kolʼa",
            "Bitʼə",
            "Misʼa"
        ],
        "trs": "Stepan, Kolya, Vitya, Misya.",
        "wlength": 4
    },
    {
        "ID": "inelevenki6840893944_104_109",
        "abbrkey": {},
        "ancestors": [
            {
                "id": "tung1282",
                "label": "Tungusic"
            },
            {
                "id": "nort3417",
                "label": "Northeastern Tungusic"
            },
            {
                "id": "nort3147",
                "label": "Northern Tungusic"
            }
        ],
        "book_metalanguage": "stan1293",
        "categories": [
            "NOM",
            "PST",
            "SG"
        ],
        "citation": "https://hdl.handle.net/11022/0000-0007-FE38-D",
        "clength": 24,
        "coords": [
            94.689,
            61.972
        ],
        "countries": [
            {
                "ISO3166": "CN",
                "label": "China"
            },
            {
                "ISO3166": "MN",
                "label": "Mongolia"
            },
            {
                "ISO3166": "RU",
                "label": "Russian Federation"
            }
        ],
        "doc_ID": 6840893944,
        "entities": [],
        "html": "<div class=\"imtblocks\">\n\t<div class=\"imtblock\">\n\t\t<div class=\"srcblock\">_</div>\n\t\t<div class=\"glossblock\">_</div>\n\t</div>\n\t<div class=\"imtblock\">\n\t\t<div class=\"srcblock\">_</div>\n\t\t<div class=\"glossblock\">_</div>\n\t</div>\n\t<div class=\"imtblock\">\n\t\t<div class=\"srcblock\">digin</div>\n\t\t<div class=\"glossblock\">four</div>\n\t</div>\n\t<div class=\"imtblock\">\n\t\t<div class=\"srcblock\">omolgi</div>\n\t\t<div class=\"glossblock\">boy.[NOM]</div>\n\t</div>\n\t<div class=\"imtblock\">\n\t\t<div class=\"srcblock\">bi-so-n</div>\n\t\t<div class=\"glossblock\">be-PST-3SG</div>\n\t</div>\n</div>\n",
        "imtwordsbare": [
            "_",
            "_",
            "four",
            "boy.[NOM]",
            "be-PST-3SG"
        ],
        "language_glottocode": "even1259",
        "language_iso6393": "evn",
        "language_name": "Evenki",
        "licence": "https://creativecommons.org/licenses/by-nc-sa/4.0/",
        "macroareas": [
            "Eurasia"
        ],
        "parententities": [],
        "provider": "inelevenki",
        "rightsholder": "Däbritz, Chris Lasse; Gusev, Valentin; Stoynova, Natalia. 2024. INEL Evenki Corpus. Version 2.0. Publication date 2024-12-31. Archived at Universität Hamburg. https://hdl.handle.net/11022/0000-0007-FE38-D",
        "srcwordsbare": [
            "_",
            "_",
            "digin",
            "omolgi",
            "bi-so-n"
        ],
        "trs": "Poor ones(?), (…) it was four boys.",
        "wlength": 5
    },
    {
        "ID": "inelevenki6840893944_110_114",
        "abbrkey": {},
        "ancestors": [
            {
                "id": "tung1282",
                "label": "Tungusic"
            },
            {
                "id": "nort3417",
                "label": "Northeastern Tungusic"
            },
            {
                "id": "nort3147",
                "label": "Northern Tungusic"
            }
        ],
        "book_metalanguage": "stan1293",
        "categories": [],
        "citation": "https://hdl.handle.net/11022/0000-0007-FE38-D",
        "clength": 7,
        "coords": [
            94.689,
            61.972
        ],
        "countries": [
            {
                "ISO3166": "CN",
                "label": "China"
            },
            {
                "ISO3166": "MN",
                "label": "Mongolia"
            },
            {
                "ISO3166": "RU",
                "label": "Russian Federation"
            }
        ],
        "doc_ID": 6840893944,
        "entities": [],
        "html": "<div class=\"imtblocks\">\n\t<div class=\"imtblock\">\n\t\t<div class=\"srcblock\">_</div>\n\t\t<div class=\"glossblock\">_</div>\n\t</div>\n\t<div class=\"imtblock\">\n\t\t<div class=\"srcblock\">_</div>\n\t\t<div class=\"glossblock\">_</div>\n\t</div>\n\t<div class=\"imtblock\">\n\t\t<div class=\"srcblock\">_</div>\n\t\t<div class=\"glossblock\">_</div>\n\t</div>\n\t<div class=\"imtblock\">\n\t\t<div class=\"srcblock\">_</div>\n\t\t<div class=\"glossblock\">_</div>\n\t</div>\n</div>\n",
        "imtwordsbare": [
            "_",
            "_",
            "_",
            "_"
        ],
        "language_glottocode": "even1259",
        "language_iso6393": "evn",
        "language_name": "Evenki",
        "licence": "https://creativecommons.org/licenses/by-nc-sa/4.0/",
        "macroareas": [
            "Eurasia"
        ],
        "parententities": [],
        "provider": "inelevenki",
        "rightsholder": "Däbritz, Chris Lasse; Gusev, Valentin; Stoynova, Natalia. 2024. INEL Evenki Corpus. Version 2.0. Publication date 2024-12-31. Archived at Universität Hamburg. https://hdl.handle.net/11022/0000-0007-FE38-D",
        "srcwordsbare": [
            "_",
            "_",
            "_",
            "_"
        ],
        "trs": "Only one last [boy] stayed.",
        "wlength": 4
    },
    {
        "ID": "inelevenki6840893944_115_118",
        "abbrkey": {},
        "ancestors": [
            {
                "id": "tung1282",
                "label": "Tungusic"
            },
            {
                "id": "nort3417",
                "label": "Northeastern Tungusic"
            },
            {
                "id": "nort3147",
                "label": "Northern Tungusic"
            }
        ],
        "book_metalanguage": "stan1293",
        "categories": [
            "ABL",
            "NOM"
        ],
        "citation": "https://hdl.handle.net/11022/0000-0007-FE38-D",
        "clength": 24,
        "coords": [
            94.689,
            61.972
        ],
        "countries": [
            {
                "ISO3166": "CN",
                "label": "China"
            },
            {
                "ISO3166": "MN",
                "label": "Mongolia"
            },
            {
                "ISO3166": "RU",
                "label": "Russian Federation"
            }
        ],
        "doc_ID": 6840893944,
        "entities": [],
        "html": "<div class=\"imtblocks\">\n\t<div class=\"imtblock\">\n\t\t<div class=\"srcblock\">dʼan-duk</div>\n\t\t<div class=\"glossblock\">ten-ABL</div>\n\t</div>\n\t<div class=\"imtblock\">\n\t\t<div class=\"srcblock\">umukon</div>\n\t\t<div class=\"glossblock\">one.[NOM]</div>\n\t</div>\n\t<div class=\"imtblock\">\n\t\t<div class=\"srcblock\">hutə-duk</div>\n\t\t<div class=\"glossblock\">child-ABL</div>\n\t</div>\n</div>\n",
        "imtwordsbare": [
            "ten-ABL",
            "one.[NOM]",
            "child-ABL"
        ],
        "language_glottocode": "even1259",
        "language_iso6393": "evn",
        "language_name": "Evenki",
        "licence": "https://creativecommons.org/licenses/by-nc-sa/4.0/",
        "macroareas": [
            "Eurasia"
        ],
        "parententities": [],
        "provider": "inelevenki",
        "rightsholder": "Däbritz, Chris Lasse; Gusev, Valentin; Stoynova, Natalia. 2024. INEL Evenki Corpus. Version 2.0. Publication date 2024-12-31. Archived at Universität Hamburg. https://hdl.handle.net/11022/0000-0007-FE38-D",
        "srcwordsbare": [
            "dʼan-duk",
            "umukon",
            "hutə-duk"
        ],
        "trs": "Out of eleven children.",
        "wlength": 3
    }
]