[
    {
        "ID": "inelevenki3032333726_0_3",
        "abbrkey": {},
        "ancestors": [
            {
                "id": "tung1282",
                "label": "Tungusic"
            },
            {
                "id": "nort3417",
                "label": "Northeastern Tungusic"
            },
            {
                "id": "nort3147",
                "label": "Northern Tungusic"
            }
        ],
        "book_metalanguage": "stan1293",
        "categories": [
            "CNG",
            "NEG",
            "NOM",
            "PST",
            "SG"
        ],
        "citation": "https://hdl.handle.net/11022/0000-0007-FE38-D",
        "clength": 20,
        "coords": [
            94.689,
            61.972
        ],
        "countries": [
            {
                "ISO3166": "CN",
                "label": "China"
            },
            {
                "ISO3166": "MN",
                "label": "Mongolia"
            },
            {
                "ISO3166": "RU",
                "label": "Russian Federation"
            }
        ],
        "doc_ID": 3032333726,
        "entities": [],
        "html": "<div class=\"imtblocks\">\n\t<div class=\"imtblock\">\n\t\t<div class=\"srcblock\">e-matča ə-ča-m ša-rə</div>\n\t\t<div class=\"glossblock\">what-NEG1.[NOM] NEG-PST-1SG know-CNG</div>\n\t</div>\n</div>\n",
        "imtwordsbare": [
            "what-NEG1.[NOM] NEG-PST-1SG know-CNG"
        ],
        "language_glottocode": "even1259",
        "language_iso6393": "evn",
        "language_name": "Evenki",
        "license": "https://creativecommons.org/licenses/by/4.0",
        "parententities": [],
        "provider": "inelevenki",
        "srcwordsbare": [
            "e-matča ə-ča-m ša-rə"
        ],
        "trs": "I don't know anything.",
        "wlength": 1
    },
    {
        "ID": "inelevenki3032333726_3_7",
        "abbrkey": {},
        "ancestors": [
            {
                "id": "tung1282",
                "label": "Tungusic"
            },
            {
                "id": "nort3417",
                "label": "Northeastern Tungusic"
            },
            {
                "id": "nort3147",
                "label": "Northern Tungusic"
            }
        ],
        "book_metalanguage": "stan1293",
        "categories": [
            "CNG",
            "FUT",
            "NEG",
            "NOM",
            "PST",
            "SG"
        ],
        "citation": "https://hdl.handle.net/11022/0000-0007-FE38-D",
        "clength": 33,
        "coords": [
            94.689,
            61.972
        ],
        "countries": [
            {
                "ISO3166": "CN",
                "label": "China"
            },
            {
                "ISO3166": "MN",
                "label": "Mongolia"
            },
            {
                "ISO3166": "RU",
                "label": "Russian Federation"
            }
        ],
        "doc_ID": 3032333726,
        "entities": [],
        "html": "<div class=\"imtblocks\">\n\t<div class=\"imtblock\">\n\t\t<div class=\"srcblock\">əta-m ulɣučan-i e-matči omɣo-čo-w</div>\n\t\t<div class=\"glossblock\">NEG.FUT-1SG tell-CNG what-NEG1.[NOM] forget-PST-1SG</div>\n\t</div>\n</div>\n",
        "imtwordsbare": [
            "NEG.FUT-1SG tell-CNG what-NEG1.[NOM] forget-PST-1SG"
        ],
        "language_glottocode": "even1259",
        "language_iso6393": "evn",
        "language_name": "Evenki",
        "license": "https://creativecommons.org/licenses/by/4.0",
        "parententities": [],
        "provider": "inelevenki",
        "srcwordsbare": [
            "əta-m ulɣučan-i e-matči omɣo-čo-w"
        ],
        "trs": "I won't say anything — I've forgotten.",
        "wlength": 1
    }
]